rtl/instr_mem.v
// ============================================
// Instruction Memory (ROM)
// RISC-V Lite CPU — Week 3
// ============================================
module instr_mem (
    input  wire [7:0]  addr,        // PC value — which instruction?
    output wire [15:0] instruction  // 16-bit instruction out
);
    // 256 locations x 16-bit wide memory
    reg [15:0] mem [0:255];

    // Preload a few sample instructions for testing
    initial begin
        mem[0] = 16'h1123;  // e.g. ADD R1, R2, R3  (dummy encoding)
        mem[1] = 16'h2145;  // e.g. SUB R1, R4, R5
        mem[2] = 16'h3167;  // e.g. AND R1, R6, R7
        mem[3] = 16'h0000;  // NOP
        // ... baaki locations default 0
    end

    // Combinational read — address kudutha udane instruction varum
    assign instruction = mem[addr];
endmodule

rtl/pc.v
// ============================================
// Program Counter (PC)
// RISC-V Lite CPU — Week 3
// ============================================
module pc (
    input  wire       clk,
    input  wire       rst,
    input  wire        pc_write,   // stall panna venuma nu control
    input  wire [7:0] pc_next,    // next PC value (branch/jump target or PC+1)
    output reg  [7:0] pc_out      // current PC value
);
    always @(posedge clk or posedge rst) begin
        if (rst)
            pc_out <= 8'd0;          // start from instruction 0
        else if (pc_write)
            pc_out <= pc_next;       // update PC
    end
endmodule

rtl/if_stage.v
// ============================================
// IF Stage — PC + Instruction Memory connected
// RISC-V Lite CPU — Week 3
// ============================================
module if_stage (
    input  wire        clk,
    input  wire        rst,
    input  wire        pc_write,
    input  wire [7:0]  pc_next,     // adutha PC evlo nu vera logic sollum
    output wire [7:0]  pc_out,      // current PC (debug/next-stage-ku)
    output wire [15:0] instruction  // fetched instruction
);
    wire [7:0] pc_current;

    // Program Counter
    pc pc_unit (
        .clk(clk),
        .rst(rst),
        .pc_write(pc_write),
        .pc_next(pc_next),
        .pc_out(pc_current)
    );

    // Instruction Memory
    instr_mem imem_unit (
        .addr(pc_current),
        .instruction(instruction)
    );

    assign pc_out = pc_current;
endmodule

testbench/if_stage_tb.v
// ============================================
// IF Stage Testbench
// ============================================
`timescale 1ns/1ps
module if_stage_tb;

    reg        clk, rst, pc_write;
    reg  [7:0] pc_next;
    wire [7:0] pc_out;
    wire [15:0] instruction;

    if_stage uut (
        .clk(clk),
        .rst(rst),
        .pc_write(pc_write),
        .pc_next(pc_next),
        .pc_out(pc_out),
        .instruction(instruction)
    );

    initial begin
        $dumpfile("sim_output/if_wave.vcd");
        $dumpvars(0, if_stage_tb);
    end

    always #5 clk = ~clk;

    initial begin
        clk = 0; rst = 1; pc_write = 0; pc_next = 8'd0;

        $display("=====================================");
        $display("      IF Stage Testbench Start        ");
        $display("=====================================");

        #10 rst = 0;

        // Simple PC increment simulation: 0 -> 1 -> 2 -> 3
        pc_write = 1;

        pc_next = 8'd0; #10;
        $display("PC=%0d, Instruction=%h", pc_out, instruction);

        pc_next = 8'd1; #10;
        $display("PC=%0d, Instruction=%h", pc_out, instruction);

        pc_next = 8'd2; #10;
        $display("PC=%0d, Instruction=%h", pc_out, instruction);

        pc_next = 8'd3; #10;
        $display("PC=%0d, Instruction=%h", pc_out, instruction);

        $display("=====================================");
        $display("      All Tests Done!                 ");
        $display("=====================================");
        $finish;
    end
endmodule

sim_output/if_wave.vcd
$date
	Sat Aug 22 22:22:52 2026
$end
$version
	Icarus Verilog
$end
$timescale
	1ps
$end
$scope module if_stage_tb $end
$var wire 8 ! pc_out [7:0] $end
$var wire 16 " instruction [15:0] $end
$var reg 1 # clk $end
$var reg 8 $ pc_next [7:0] $end
$var reg 1 % pc_write $end
$var reg 1 & rst $end
$scope module uut $end
$var wire 1 # clk $end
$var wire 8 ' pc_next [7:0] $end
$var wire 8 ( pc_out [7:0] $end
$var wire 1 % pc_write $end
$var wire 1 & rst $end
$var wire 8 ) pc_current [7:0] $end
$var wire 16 * instruction [15:0] $end
$scope module imem_unit $end
$var wire 16 + instruction [15:0] $end
$var wire 8 , addr [7:0] $end
$upscope $end
$scope module pc_unit $end
$var wire 1 # clk $end
$var wire 8 - pc_next [7:0] $end
$var wire 1 % pc_write $end
$var wire 1 & rst $end
$var reg 8 . pc_out [7:0] $end
$upscope $end
$upscope $end
$upscope $end
$enddefinitions $end
$comment Show the parameter values. $end
$dumpall
$end
#0
$dumpvars
b0 .
b0 -
b0 ,
b1000100100011 +
b1000100100011 *
b0 )
b0 (
b0 '
1&
0%
b0 $
0#
b1000100100011 "
b0 !
$end
#5000
1#
#10000
0#
1%
0&
#15000
1#
#20000
0#
b1 $
b1 '
b1 -
#25000
b10000101000101 "
b10000101000101 *
b10000101000101 +
b1 !
b1 (
b1 )
b1 ,
b1 .
1#
#30000
0#
b10 $
b10 '
b10 -
#35000
b11000101100111 "
b11000101100111 *
b11000101100111 +
b10 !
b10 (
b10 )
b10 ,
b10 .
1#
#40000
0#
b11 $
b11 '
b11 -
#45000
b0 "
b0 *
b0 +
b11 !
b11 (
b11 )
b11 ,
b11 .
1#
