rtl/reg_file.v
// ============================================
// Register File — 8 x 8-bit registers
// RISC-V Lite CPU — Week 2
// Karthik / Vector X
// ============================================

module reg_file (
    input  wire       clk,        // Clock
    input  wire       rst,        // Reset
    
    // Read Port 1 (Rs1)
    input  wire [2:0] rs1,        // Register select 1
    output wire [7:0] rs1_data,   // Register 1 data out
    
    // Read Port 2 (Rs2)
    input  wire [2:0] rs2,        // Register select 2
    output wire [7:0] rs2_data,   // Register 2 data out
    
    // Write Port (Rd)
    input  wire [2:0] rd,         // Destination register
    input  wire [7:0] rd_data,    // Data to write
    input  wire       wr_en       // Write enable
);

    // 8 registers, each 8-bit wide
    reg [7:0] registers [0:7];

    integer i;

    // Reset + Write logic
    always @(posedge clk or posedge rst) begin
        if (rst) begin
            // Reset — all registers 0
            for (i = 0; i < 8; i = i + 1)
                registers[i] <= 8'd0;
        end
        else if (wr_en && rd != 3'd0) begin
            // Write — R0 always 0, never write!
            registers[rd] <= rd_data;
        end
    end

    // Read logic — combinational (instant)
    assign rs1_data = (rs1 == 3'd0) ? 8'd0 : registers[rs1];
    assign rs2_data = (rs2 == 3'd0) ? 8'd0 : registers[rs2];

endmodule

testbench/reg_file_tb.v
// ============================================
// Register File Testbench
// ============================================

`timescale 1ns/1ps

module reg_file_tb;

    reg        clk, rst;
    reg  [2:0] rs1, rs2, rd;
    reg  [7:0] rd_data;
    reg        wr_en;
    wire [7:0] rs1_data, rs2_data;

    // Connect Register File
    reg_file uut (
        .clk(clk),
        .rst(rst),
        .rs1(rs1),      .rs1_data(rs1_data),
        .rs2(rs2),      .rs2_data(rs2_data),
        .rd(rd),        .rd_data(rd_data),
        .wr_en(wr_en)
    );

    // Waveform dump
    initial begin
        $dumpfile("sim_output/reg_wave.vcd");
        $dumpvars(0, reg_file_tb);
    end

    // Clock — 10ns period
    always #5 clk = ~clk;

    initial begin
        // Init
        clk = 0; rst = 1;
        rs1 = 0; rs2 = 0;
        rd  = 0; rd_data = 0;
        wr_en = 0;

        $display("=====================================");
        $display("   Register File Testbench Start     ");
        $display("=====================================");

        // Reset release
        #10 rst = 0;

        // Test 1: Write 42 to R1
        rd = 3'd1; rd_data = 8'd42; wr_en = 1;
        #10;
        $display("Write R1 = 42");

        // Test 2: Write 99 to R3
        rd = 3'd3; rd_data = 8'd99; wr_en = 1;
        #10;
        $display("Write R3 = 99");

        // Test 3: Read R1 + R3
        wr_en = 0;
        rs1 = 3'd1; rs2 = 3'd3;
        #10;
        $display("Read R1 = %0d (expect 42)", rs1_data);
        $display("Read R3 = %0d (expect 99)", rs2_data);

        // Test 4: Try write to R0 (should stay 0!)
        rd = 3'd0; rd_data = 8'd255; wr_en = 1;
        #10;
        rs1 = 3'd0;
        wr_en = 0;
        #10;
        $display("Read R0 = %0d (expect 0 always!)", rs1_data);

        // Test 5: Write R1, read immediately
        rd = 3'd1; rd_data = 8'd77; wr_en = 1;
        #10;
        rs1 = 3'd1; wr_en = 0;
        #10;
        $display("R1 updated = %0d (expect 77)", rs1_data);

        // Test 6: ALU result store pannunga (real use case)
        // ADD R2 = R1 + R3 → 77 + 99 = 176
        rd = 3'd2; rd_data = 8'd176; wr_en = 1;
        #10;
        rs1 = 3'd1; rs2 = 3'd2; wr_en = 0;
        #10;
        $display("R1=%0d, R2=%0d (ALU result stored)", rs1_data, rs2_data);

        $display("=====================================");
        $display("   All Tests Done!                  ");
        $display("=====================================");
        $finish;
    end

endmodule

sim_output/reg_wave.vcd
$date
	Sat Aug 22 22:04:52 2026
$end
$version
	Icarus Verilog
$end
$timescale
	1ps
$end
$scope module reg_file_tb $end
$var wire 8 ! rs2_data [7:0] $end
$var wire 8 " rs1_data [7:0] $end
$var reg 1 # clk $end
$var reg 3 $ rd [2:0] $end
$var reg 8 % rd_data [7:0] $end
$var reg 3 & rs1 [2:0] $end
$var reg 3 ' rs2 [2:0] $end
$var reg 1 ( rst $end
$var reg 1 ) wr_en $end
$scope module uut $end
$var wire 1 # clk $end
$var wire 3 * rd [2:0] $end
$var wire 8 + rd_data [7:0] $end
$var wire 3 , rs1 [2:0] $end
$var wire 3 - rs2 [2:0] $end
$var wire 1 ( rst $end
$var wire 1 ) wr_en $end
$var wire 8 . rs2_data [7:0] $end
$var wire 8 / rs1_data [7:0] $end
$var integer 32 0 i [31:0] $end
$upscope $end
$upscope $end
$enddefinitions $end
$comment Show the parameter values. $end
$dumpall
$end
#0
$dumpvars
b1000 0
b0 /
b0 .
b0 -
b0 ,
b0 +
b0 *
0)
1(
b0 '
b0 &
b0 %
b0 $
0#
b0 "
b0 !
$end
#5000
b1000 0
1#
#10000
0#
1)
b101010 %
b101010 +
b1 $
b1 *
0(
#15000
1#
#20000
0#
b1100011 %
b1100011 +
b11 $
b11 *
#25000
1#
#30000
b1100011 !
b1100011 .
b101010 "
b101010 /
0#
b11 '
b11 -
b1 &
b1 ,
0)
#35000
1#
#40000
0#
1)
b11111111 %
b11111111 +
b0 $
b0 *
#45000
1#
#50000
b0 "
b0 /
0#
0)
b0 &
b0 ,
#55000
1#
#60000
0#
1)
b1001101 %
b1001101 +
b1 $
b1 *
#65000
1#
#70000
b1001101 "
b1001101 /
0#
0)
b1 &
b1 ,
#75000
1#
#80000
0#
1)
b10110000 %
b10110000 +
b10 $
b10 *
#85000
1#
#90000
b10110000 !
b10110000 .
0#
0)
b10 '
b10 -
